eplremade/__init__.py
eplremade/algorithms/__init__.py
eplremade/algorithms/sorting.py
eplremade/algorithms/visualizer_beta.py
eplremade/circuit/__init__.py
eplremade/circuit/board.py
eplremade/complexnum/__init__.py
eplremade/complexnum/complexnum.py
eplremade/complexnum/tokenizer.py
eplremade/ctests/__init__.py
eplremade/ctests/testpy.py
eplremade/matrixop/__init__.py
eplremade/matrixop/matrixop.py
eplremade/rfunctools/__init__.py
eplremade/rfunctools/cache.py
eplremade/rfunctools/customerrors.py
eplremade/rfunctools/decor.py
eplremade/rmath/__init__.py
eplremade/rmath/derive.py
eplremade/rmath/function.py
eplremade/rmath/rmath.py
eplremade/rmath/rmath.pyi
eplremade/rnetwork/__init__.py
eplremade/rnetwork/rnetwork.py
eplremade/rtype/__init__.py
eplremade/rtype/rtype.py
eplremade-1.0.0.dist-info/LICENSE
eplremade-1.0.0.dist-info/METADATA
eplremade-1.0.0.dist-info/WHEEL
eplremade-1.0.0.dist-info/top_level.txt
eplremade-1.0.0.dist-info/RECORD
