Metadata-Version: 2.1
Name: eplremade
Version: 1.0.0
Summary: Every Python Library Remade, a project to improve base Python modules and libraries.
Home-page: https://github.com/Silicon27/EPLRemade
Author: Silicon Yang
Author-email: yangsilicon@gmail.com
Classifier: Programming Language :: Python :: 3
Classifier: Programming Language :: Python :: 3.10
Classifier: Programming Language :: Python :: 3.11
Classifier: License :: OSI Approved :: MIT License
Classifier: Operating System :: OS Independent
Requires-Python: >=3.10
License-File: LICENSE
